rated_parser/__init__.py
rated_parser/exceptions.py
rated_parser/core/__init__.py
rated_parser/core/parser.py
rated_parser/core/constants/__init__.py
rated_parser/core/constants/http.py
rated_parser/payloads/__init__.py
rated_parser/payloads/encryption.py
rated_parser/payloads/log_patterns.py
rated_parser/payloads/metric_patterns.py
rated_parser/payloads/transformations.py
rated_parser/payloads/types.py
rated_parser/strategies/__init__.py
rated_parser/strategies/base.py
rated_parser/strategies/grok_parser.py
rated_parser/strategies/json_parser.py
rated_parser/utils/__init__.py
rated_parser/utils/factory.py
rated_parser-1.0.1.dist-info/LICENSE.md
rated_parser-1.0.1.dist-info/METADATA
rated_parser-1.0.1.dist-info/WHEEL
rated_parser-1.0.1.dist-info/top_level.txt
rated_parser-1.0.1.dist-info/RECORD
